setup.py
amiandopy/__init__.py
amiandopy/amiando_api.py
amiandopy/version.py
amiandopy.egg-info/PKG-INFO
amiandopy.egg-info/SOURCES.txt
amiandopy.egg-info/dependency_links.txt
amiandopy.egg-info/not-zip-safe
amiandopy.egg-info/requires.txt
amiandopy.egg-info/top_level.txt