Metadata-Version: 1.0
Name: amiandopy
Version: 0.1
Summary: amiandoPy makes it really easy to interact with amiando's API
Home-page: http://github.com/ledil/amiandopy
Author: Leonardo Di Lella
Author-email: leonardo.dilella@mobileapart.com
License: UNKNOWN
Platform: UNKNOWN
Classifier: Development Status :: 5 - Production/Stable
Classifier: Intended Audience :: Developers
Classifier: Natural Language :: English
Classifier: License :: OSI Approved :: MIT License
Classifier: Programming Language :: Python
Classifier: Programming Language :: Python :: 2.6
Classifier: Programming Language :: Python :: 2.7
